cdswjoblauncher/__init__.py
cdswjoblauncher/cdsw/.gitignore
cdswjoblauncher/cdsw/__init__.py
cdswjoblauncher/cdsw/cdsw_common.py
cdswjoblauncher/cdsw/cdsw_config.py
cdswjoblauncher/cdsw/cdsw_runner.py
cdswjoblauncher/cdsw/constants.py
cdswjoblauncher/cdsw/libreloader/__init__.py
cdswjoblauncher/cdsw/libreloader/reload_dependencies.py
cdswjoblauncher/cdsw/start_job.py
cdswjoblauncher/cdsw/testutils/__init__.py
cdswjoblauncher/cdsw/testutils/test_utils.py
cdswjoblauncher/cdsw/utils.py
cdswjoblauncher/cli/__init__.py
cdswjoblauncher/cli/cli.py
cdswjoblauncher/cli/commands/config/__init__.py
cdswjoblauncher/commands/__init__.py
cdswjoblauncher/commands/cmd_type.py
cdswjoblauncher/commands/send_latest_command_data_in_mail.py
cdswjoblauncher/commands/zip_latest_command_data.py
cdswjoblauncher/contract.py
cdswjoblauncher/core/__init__.py
cdswjoblauncher/core/config.py
cdswjoblauncher/core/context.py
cdswjoblauncher/core/error.py
cdswjoblauncher/core/handler.py
cdswjoblauncher/core/module.py
cdsw_job_launcher-1.0.21.dist-info/LICENSE
cdsw_job_launcher-1.0.21.dist-info/METADATA
cdsw_job_launcher-1.0.21.dist-info/WHEEL
cdsw_job_launcher-1.0.21.dist-info/RECORD
