Metadata-Version: 2.1
Name: cdsw-job-launcher
Version: 1.0.21
Summary: 
Author: Szilard Nemeth
Author-email: szilard.nemeth88@gmail.com
Requires-Python: >=3.8,<4.0
Classifier: Programming Language :: Python :: 3
Classifier: Programming Language :: Python :: 3.8
Classifier: Programming Language :: Python :: 3.9
Classifier: Programming Language :: Python :: 3.10
Classifier: Programming Language :: Python :: 3.11
Classifier: Programming Language :: Python :: 3.12
Requires-Dist: dacite (>=1.8.1,<2.0.0)
Requires-Dist: dataclasses-json (>=0.5.7,<0.6.0)
Requires-Dist: google-api-wrapper2 (>=1.0.13,<2.0.0)
Requires-Dist: pytest (>=6.2.3,<6.3.0)
Requires-Dist: python-common-lib (>=1.0.12,<2.0.0)
Requires-Dist: requests (>=2.28.1,<3.0.0)
Requires-Dist: rich (>=13.7.1,<14.0.0)
